markus_autotest_helpers_c/__init__.py
markus_autotest_helpers_c-0.1.0.dist-info/WHEEL
markus_autotest_helpers_c-0.1.0.dist-info/METADATA
markus_autotest_helpers_c-0.1.0.dist-info/RECORD
